pygravit/__init__.py
pygravit/_pygravit.py
pygravit/exceptions.py
pygravit/test.py
pygravit-1.0.0.0.dist-info/LICENSE
pygravit-1.0.0.0.dist-info/METADATA
pygravit-1.0.0.0.dist-info/WHEEL
pygravit-1.0.0.0.dist-info/top_level.txt
pygravit-1.0.0.0.dist-info/RECORD
