Metadata-Version: 2.1
Name: pygravit
Version: 1.0.0.0
Summary: Module for managing accounts in GravitLauncher Database
Home-page: https://github.com/Frontalvlad-GitHub/PyGravit
Author: Frontalvlad
Author-email: frontalvlad@vk.com
License: GNU General Public License v3.0
Download-URL: https://github.com/Frontalvlad-GitHub/GravitPy/releases/tag/v1.0.0.0
Platform: UNKNOWN
License-File: LICENSE
Requires-Dist: pymysql
Requires-Dist: bcrypt
